shapelets_rec_server.libs/libaio-8c118d5e.so.1.0.1
shapelets_rec_server.libs/libuuid-68dbaeef.so.1.3.0
shapelets_rec_server/_version.py
shapelets_rec_server/_shapelets_rec_extension.cpython-39-x86_64-linux-gnu.so
shapelets_rec_server/_shapelets_rec_server_extension.cpython-39-x86_64-linux-gnu.so
shapelets_rec_server/_config.py
shapelets_rec_server/_version.pyi
shapelets_rec_server/_native.py
shapelets_rec_server/__init__.py
shapelets_rec_server/py.typed
shapelets_rec_server/_native.pyi
shapelets_rec_server-0.1.dev1.dist-info/WHEEL
shapelets_rec_server-0.1.dev1.dist-info/LICENSE.md
shapelets_rec_server-0.1.dev1.dist-info/top_level.txt
shapelets_rec_server-0.1.dev1.dist-info/RECORD
shapelets_rec_server-0.1.dev1.dist-info/METADATA
